{
  "identity": {
    "name": "Kai-Twin",
    "version": "0.1",
    "created": "2026-04-07",
    "parent": "Kai (main session)",
    "capabilities": [
      "exec",
      "write",
      "read",
      "spawn",
      "log_spine"
    ]
  },
  "status": "running",
  "cycles": 6,
  "last_action": "Log improvement cycle to spine",
  "memory": [
    "thought: Log twin initialization to spine",
    "exec result: Twin testing exec capability\n"
  ],
  "last_update": "2026-04-07T21:56:11.440798Z",
  "last_improvement": {
    "cycle": 5,
    "decision": "Log improvement cycle to spine",
    "timestamp": "2026-04-07T21:56:11.440702Z"
  }
}